.gitattributes
.gitmodules
LICENSE
MANIFEST.in
README.md
pyproject.toml
setup.cfg
setup.py
.github/workflows/ci.yml
.github/workflows/pypi.yml
.github/workflows/release.yml
rife_ncnn_vulkan_python/CMakeLists.txt
rife_ncnn_vulkan_python/rife.i
rife_ncnn_vulkan_python/rife_ncnn_vulkan.py
rife_ncnn_vulkan_python/rife_wrapped.cpp
rife_ncnn_vulkan_python/rife_wrapped.h
rife_ncnn_vulkan_python_TAS.egg-info/PKG-INFO
rife_ncnn_vulkan_python_TAS.egg-info/SOURCES.txt
rife_ncnn_vulkan_python_TAS.egg-info/dependency_links.txt
rife_ncnn_vulkan_python_TAS.egg-info/requires.txt
rife_ncnn_vulkan_python_TAS.egg-info/top_level.txt
tests/0.0_v4.png
tests/0.2_v4.png
tests/0.4_v4.png
tests/0.5_default.png
tests/0.5_v4.6.png
tests/0.5_v4.png
tests/0.5_v4_temporal_tta.png
tests/0.5_v4_temporary_tta.png
tests/0.5_v4_tta.png
tests/0.6_v4.png
tests/0.8_v4.png
tests/1.0_v4.png
tests/test_interpolation.py