Metadata-Version: 2.1
Name: rife-ncnn-vulkan-python-TAS
Version: 2.0.4
Summary: A Python FFI of nihui/rife-ncnn-vulkan achieved with SWIG
Home-page: https://github.com/NevermindNilas/rife-ncnn-vulkan-python
Author: ArchieMeng
Author-email: archiemeng@protonmail.com
Maintainer: NevermindNilas
Maintainer-email: nilascontact@gmail.com
License: AGPL3.0
Keywords: rife,ncnn,vulkan,swig
Classifier: Environment :: Console
Classifier: Programming Language :: Python
Classifier: Programming Language :: Python :: 3
Classifier: Operating System :: OS Independent
Requires-Python: >=3.6
License-File: LICENSE
Requires-Dist: pillow
